tests/metrics/__init__.py
tests/metrics/test_avg_workflow_size_count.py
tests/metrics/test_lcot_count.py
tests/metrics/test_num_artifact_types_count.py
tests/metrics/test_num_capabilities_count.py
tests/metrics/test_num_capability_types_count.py
tests/metrics/test_num_data_types_count.py
tests/metrics/test_num_group_types_count.py
tests/metrics/test_num_imports_count.py
tests/metrics/test_num_inputs_count.py
tests/metrics/test_num_interfaces_count.py
tests/metrics/test_num_node_templates_count.py
tests/metrics/test_num_node_types_count.py
tests/metrics/test_num_parameters_count.py
tests/metrics/test_num_policy_types_count.py
tests/metrics/test_num_properties_count.py
tests/metrics/test_num_relationship_templates_count.py
tests/metrics/test_num_relationship_types_count.py
tests/metrics/test_num_requirements_count.py
tests/metrics/test_num_shell_scripts_count.py
tests/metrics/test_num_workflows_count.py
tests/yml/__init__.py
tests/yml/test_lines_blank_count.py
tests/yml/test_lines_code_count.py
tests/yml/test_lines_code_init.py
tests/yml/test_lines_comment_count.py
tests/yml/test_num_keys_count.py
tests/yml/test_num_suspicious_comments_count.py
tests/yml/test_num_tokens_count.py
tests/yml/test_text_entropy_count.py
toscametrics/__init__.py
toscametrics/blueprint_metric.py
toscametrics/command_line.py
toscametrics/import_metrics.py
toscametrics/metrics_extractor.py
toscametrics/utils.py
toscametrics/blueprint/__init__.py
toscametrics/blueprint/avg_workflow_size.py
toscametrics/blueprint/lcot.py
toscametrics/blueprint/num_artifact_types.py
toscametrics/blueprint/num_capabilities.py
toscametrics/blueprint/num_capability_types.py
toscametrics/blueprint/num_data_types.py
toscametrics/blueprint/num_group_types.py
toscametrics/blueprint/num_imports.py
toscametrics/blueprint/num_inputs.py
toscametrics/blueprint/num_interfaces.py
toscametrics/blueprint/num_node_templates.py
toscametrics/blueprint/num_node_types.py
toscametrics/blueprint/num_parameters.py
tosca_metrics-0.0.11.dist-info/LICENSE
tosca_metrics-0.0.11.dist-info/METADATA
tosca_metrics-0.0.11.dist-info/WHEEL
tosca_metrics-0.0.11.dist-info/entry_points.txt
tosca_metrics-0.0.11.dist-info/top_level.txt
tosca_metrics-0.0.11.dist-info/RECORD
