Metadata-Version: 2.1
Name: tosca-metrics
Version: 0.0.11
Summary: A module to extract metrics rom TOSCA blueprints
Home-page: UNKNOWN
Author: Stefano Dalla Palma
Author-email: stefano.dallapalma0@gmail.com
Maintainer: Stefano Dalla Palma
License: UNKNOWN
Platform: UNKNOWN
Classifier: Development Status :: 3 - Alpha
Classifier: Intended Audience :: Developers
Classifier: Programming Language :: Python :: 3.7
Classifier: Programming Language :: Python :: 3.8
Classifier: License :: OSI Approved :: Apache Software License
Classifier: Topic :: Software Development :: Libraries :: Python Modules
Classifier: Operating System :: OS Independent
Requires-Dist: PyYAML (==5.4)
Requires-Dist: pytest (==4.5.0)
Requires-Dist: pytest-cov (==2.7.1)
Requires-Dist: python-interface (==1.5.1)
Requires-Dist: statistics (==1.0.3.5)
Requires-Dist: parameterized (==0.7.0)
